job_seeker/__init__.py
job_seeker/downloader.py
job_seeker-0.0.5.dist-info/LICENSE
job_seeker-0.0.5.dist-info/METADATA
job_seeker-0.0.5.dist-info/WHEEL
job_seeker-0.0.5.dist-info/top_level.txt
job_seeker-0.0.5.dist-info/RECORD
