Metadata-Version: 2.1
Name: job-seeker
Version: 0.0.5
Summary: An utility downloader for a job search at seek.com.au
Home-page: https://github.com/PyBites-Open-Source/job-seeker
Author: Pedro Junqueira
Author-email: pedrocj@gmail.com
Project-URL: Bug Tracker, https://github.com/PyBites-Open-Source/job-seeker/issues
Classifier: License :: OSI Approved :: MIT License
Classifier: Operating System :: OS Independent
Classifier: Programming Language :: Python
Classifier: Programming Language :: Python :: 3
Classifier: Programming Language :: Python :: 3.7
Classifier: Programming Language :: Python :: 3.8
Classifier: Programming Language :: Python :: 3.9
Classifier: Programming Language :: Python :: 3.10
Classifier: Framework :: Pytest
License-File: LICENSE
Requires-Dist: pandas
Requires-Dist: requests
